{"_type":"export","__export_format":4,"__export_date":"2023-11-05T04:29:18.188Z","__export_source":"insomnia.desktop.app:v8.3.0","resources":[{"_id":"req_bc47fb8872fe4672bc4d0ae29aab0067","parentId":"fld_7526fa3e78c64934925c57ba3c44b7dd","modified":1699154340022,"created":1699149383857,"url":"http://localhost:3000/offers/create","name":"post offer 1","description":"","method":"POST","body":{"mimeType":"application/json","text":"{\n\t\"name\": \"carrinho\",\n\t\"price\": 5,\n\t\"description\": \"carrinho de brinquedo\",\n\t\"minimalForFreeDelivery\": 6,\n\t\"minimalForConsolidation\": 7,\n\t\"totalAmount\": 10,\n\t\"isPublic\": true,\n\t\"companyId\": 1\n}"},"parameters":[],"headers":[{"name":"Content-Type","value":"application/json"},{"name":"User-Agent","value":"insomnia/8.3.0"}],"authentication":{},"metaSortKey":-1699149383858,"isPrivate":false,"settingStoreCookies":true,"settingSendCookies":true,"settingDisableRenderRequestBody":false,"settingEncodeUrl":true,"settingRebuildPath":true,"settingFollowRedirects":"global","_type":"request"},{"_id":"fld_7526fa3e78c64934925c57ba3c44b7dd","parentId":"fld_8a9d7e65539a414697b39cb4ddfe83d1","modified":1699151871605,"created":1699149381161,"name":"post","description":"","environment":{},"environmentPropertyOrder":null,"metaSortKey":-1699151869236,"_type":"request_group"},{"_id":"fld_8a9d7e65539a414697b39cb4ddfe83d1","parentId":"wrk_cb12f0ce5b484afe8355a8cd77e1a637","modified":1699149371392,"created":1699149371392,"name":"Offer","description":"","environment":{},"environmentPropertyOrder":null,"metaSortKey":-1699149371392,"_type":"request_group"},{"_id":"wrk_cb12f0ce5b484afe8355a8cd77e1a637","parentId":null,"modified":1698437097957,"created":1698437097957,"name":"Buy2Gether","description":"","scope":"collection","_type":"workspace"},{"_id":"req_2689c102341e447c80a2cc7adcf025e5","parentId":"fld_7526fa3e78c64934925c57ba3c44b7dd","modified":1699154343781,"created":1699152048551,"url":"http://localhost:3000/offers/create","name":"post offer 2","description":"","method":"POST","body":{"mimeType":"application/json","text":"{\n\t\"name\": \"carrinho modelo 2\",\n\t\"price\": 10,\n\t\"description\": \"carrinho de brinquedo modelo 2\",\n\t\"minimalForFreeDelivery\": 8,\n\t\"minimalForConsolidation\": 8,\n\t\"totalAmount\": 15,\n\t\"isPublic\": false,\n\t\"companyId\": 1\n}"},"parameters":[],"headers":[{"name":"Content-Type","value":"application/json"},{"name":"User-Agent","value":"insomnia/8.3.0"}],"authentication":{},"metaSortKey":-1698957611751.5,"isPrivate":false,"settingStoreCookies":true,"settingSendCookies":true,"settingDisableRenderRequestBody":false,"settingEncodeUrl":true,"settingRebuildPath":true,"settingFollowRedirects":"global","_type":"request"},{"_id":"req_1977c0ecea784c82bde89ff003500d09","parentId":"fld_8a9d7e65539a414697b39cb4ddfe83d1","modified":1699154337402,"created":1699152948687,"url":"http://localhost:3000/offers/searchAll","name":"get all offer","description":"","method":"GET","body":{},"parameters":[],"headers":[{"name":"User-Agent","value":"insomnia/8.3.0"}],"authentication":{},"metaSortKey":-1699151869186,"isPrivate":false,"settingStoreCookies":true,"settingSendCookies":true,"settingDisableRenderRequestBody":false,"settingEncodeUrl":true,"settingRebuildPath":true,"settingFollowRedirects":"global","_type":"request"},{"_id":"req_a7bda48950a748f3bed2b0fc3ccdbde9","parentId":"fld_8a9d7e65539a414697b39cb4ddfe83d1","modified":1699154348799,"created":1699151869136,"url":"http://localhost:3000/offers/search/offer/1","name":"get offer by id","description":"","method":"GET","body":{},"parameters":[],"headers":[{"name":"User-Agent","value":"insomnia/8.3.0"}],"authentication":{},"metaSortKey":-1699151869136,"isPrivate":false,"settingStoreCookies":true,"settingSendCookies":true,"settingDisableRenderRequestBody":false,"settingEncodeUrl":true,"settingRebuildPath":true,"settingFollowRedirects":"global","_type":"request"},{"_id":"req_412f1101f85d4709a7ae68cef5e4b6fd","parentId":"fld_8a9d7e65539a414697b39cb4ddfe83d1","modified":1699155867981,"created":1699152264510,"url":"http://localhost:3000/offers/search/company/1","name":"get offer by companyId","description":"","method":"GET","body":{},"parameters":[],"headers":[{"name":"User-Agent","value":"insomnia/8.3.0"}],"authentication":{},"metaSortKey":-1699150626497,"isPrivate":false,"settingStoreCookies":true,"settingSendCookies":true,"settingDisableRenderRequestBody":false,"settingEncodeUrl":true,"settingRebuildPath":true,"settingFollowRedirects":"global","_type":"request"},{"_id":"req_fe5bed2851fe42a3a4f8e9ae408edd19","parentId":"fld_8a9d7e65539a414697b39cb4ddfe83d1","modified":1699157397224,"created":1699156670226,"url":"http://localhost:3000/offers/clientsJoined/1","name":"get joined clients","description":"","method":"GET","body":{},"parameters":[],"headers":[{"name":"User-Agent","value":"insomnia/8.3.0"}],"authentication":{},"metaSortKey":-1699150315837.25,"isPrivate":false,"settingStoreCookies":true,"settingSendCookies":true,"settingDisableRenderRequestBody":false,"settingEncodeUrl":true,"settingRebuildPath":true,"settingFollowRedirects":"global","_type":"request"},{"_id":"req_b7910a29cf9e4ecf9361297f8c62220e","parentId":"fld_8a9d7e65539a414697b39cb4ddfe83d1","modified":1699154352255,"created":1699152972071,"url":"http://localhost:3000/offers/update/1","name":"update offer","description":"","method":"PUT","body":{"mimeType":"application/json","text":"{\n\t\"name\": \"carrinho modelo 1\",\n\t\"price\": 5,\n\t\"description\": \"carrinho de brinquedo modelo 1\",\n\t\"minimalForFreeDelivery\": 6,\n\t\"minimalForConsolidation\": 6,\n\t\"totalAmount\": 10,\n\t\"isPublic\": true\n}"},"parameters":[],"headers":[{"name":"Content-Type","value":"application/json"},{"name":"User-Agent","value":"insomnia/8.3.0"}],"authentication":{},"metaSortKey":-1699150005177.5,"isPrivate":false,"settingStoreCookies":true,"settingSendCookies":true,"settingDisableRenderRequestBody":false,"settingEncodeUrl":true,"settingRebuildPath":true,"settingFollowRedirects":"global","_type":"request"},{"_id":"req_e6200b1db9014592915ab77e5f9c3cf3","parentId":"fld_8a9d7e65539a414697b39cb4ddfe83d1","modified":1699158080974,"created":1699154244129,"url":"http://localhost:3000/offers/join/1/4","name":"join offer","description":"","method":"PUT","body":{},"parameters":[],"headers":[{"name":"User-Agent","value":"insomnia/8.3.0"}],"authentication":{},"metaSortKey":-1699149694517.75,"isPrivate":false,"settingStoreCookies":true,"settingSendCookies":true,"settingDisableRenderRequestBody":false,"settingEncodeUrl":true,"settingRebuildPath":true,"settingFollowRedirects":"global","_type":"request"},{"_id":"req_e4ca02a531cd4c2a8b4e0904db2eafc1","parentId":"fld_8a9d7e65539a414697b39cb4ddfe83d1","modified":1699157082398,"created":1699157074164,"url":"http://localhost:3000/offers/delete/1","name":"delete offer","description":"","method":"DELETE","body":{},"parameters":[],"headers":[{"name":"User-Agent","value":"insomnia/8.3.0"}],"authentication":{},"metaSortKey":-1699149539187.875,"isPrivate":false,"settingStoreCookies":true,"settingSendCookies":true,"settingDisableRenderRequestBody":false,"settingEncodeUrl":true,"settingRebuildPath":true,"settingFollowRedirects":"global","_type":"request"},{"_id":"req_550e3e8439704f19940388306f3c42ea","parentId":"fld_fa2e30735fa84ae4b8dd1906efbcf27c","modified":1698695693796,"created":1698695651308,"url":"http://localhost:3000/companies/create","name":"post company 1","description":"","method":"POST","body":{"mimeType":"application/json","text":"{\n \"cpfCnpj\": \"047.440.450-05\",\n \"name\": \"teste brinquedos\",\n \"email\": \"teste@teste.br\",\n \"password\": \"Teste123#\",\n \"address\": \"rua sao carlos 400\",\n \"fieldOfActivity\": \"brinquedo\"\n}"},"parameters":[],"headers":[{"name":"Content-Type","value":"application/json"},{"name":"User-Agent","value":"insomnia/8.3.0"}],"authentication":{},"metaSortKey":-1698695651308,"isPrivate":false,"settingStoreCookies":true,"settingSendCookies":true,"settingDisableRenderRequestBody":false,"settingEncodeUrl":true,"settingRebuildPath":true,"settingFollowRedirects":"global","_type":"request"},{"_id":"fld_fa2e30735fa84ae4b8dd1906efbcf27c","parentId":"fld_a5720f4de7914d308bc957af729c0471","modified":1698695646765,"created":1698695646765,"name":"post","description":"","environment":{},"environmentPropertyOrder":null,"metaSortKey":-1698695646765,"_type":"request_group"},{"_id":"fld_a5720f4de7914d308bc957af729c0471","parentId":"wrk_cb12f0ce5b484afe8355a8cd77e1a637","modified":1698436551077,"created":1698436551077,"name":"Company","description":"","environment":{},"environmentPropertyOrder":null,"metaSortKey":-1698436551077,"_type":"request_group"},{"_id":"req_0ad498c3049a47be9909e356e8df7728","parentId":"fld_fa2e30735fa84ae4b8dd1906efbcf27c","modified":1698695690789,"created":1698695680028,"url":"http://localhost:3000/companies/create","name":"post company 2","description":"","method":"POST","body":{"mimeType":"application/json","text":"{\n \"cpfCnpj\": \"037.440.450-05\",\n \"name\": \"teste roupas\",\n \"email\": \"teste@teste.br\",\n \"password\": \"Teste123#\",\n \"address\": \"rua sao carlos 400\",\n \"fieldOfActivity\": \"roupas\"\n}\n"},"parameters":[],"headers":[{"name":"Content-Type","value":"application/json"},{"name":"User-Agent","value":"insomnia/8.3.0"}],"authentication":{},"metaSortKey":-1698695091115,"isPrivate":false,"settingStoreCookies":true,"settingSendCookies":true,"settingDisableRenderRequestBody":false,"settingEncodeUrl":true,"settingRebuildPath":true,"settingFollowRedirects":"global","_type":"request"},{"_id":"req_022a2968a589482a874365726e8b30ee","parentId":"fld_fa2e30735fa84ae4b8dd1906efbcf27c","modified":1698695686052,"created":1698695682714,"url":"http://localhost:3000/companies/create","name":"post company 3","description":"","method":"POST","body":{"mimeType":"application/json","text":"{\n \"cpfCnpj\": \"057.440.450-05\",\n \"name\": \"teste alimento\",\n \"email\": \"teste@teste.br\",\n \"password\": \"Teste123#\",\n \"address\": \"rua sao carlos 400\",\n \"fieldOfActivity\": \"alimento\"\n}"},"parameters":[],"headers":[{"name":"Content-Type","value":"application/json"},{"name":"User-Agent","value":"insomnia/8.3.0"}],"authentication":{},"metaSortKey":-1698694811018.5,"isPrivate":false,"settingStoreCookies":true,"settingSendCookies":true,"settingDisableRenderRequestBody":false,"settingEncodeUrl":true,"settingRebuildPath":true,"settingFollowRedirects":"global","_type":"request"},{"_id":"req_7a006b46faad4a1782ff4af5f96fd825","parentId":"fld_a5720f4de7914d308bc957af729c0471","modified":1698694622534,"created":1698258253461,"url":"http://localhost:3000/companies/search/2","name":"get company by id","description":"","method":"GET","body":{},"parameters":[],"headers":[{"name":"User-Agent","value":"insomnia/8.3.0"}],"authentication":{},"metaSortKey":-1698436574741,"isPrivate":false,"settingStoreCookies":true,"settingSendCookies":true,"settingDisableRenderRequestBody":false,"settingEncodeUrl":true,"settingRebuildPath":true,"settingFollowRedirects":"global","_type":"request"},{"_id":"req_151d4c831cc148e0953b80bf38827cd1","parentId":"fld_a5720f4de7914d308bc957af729c0471","modified":1698694629532,"created":1698435347234,"url":"http://localhost:3000/companies/searchAll","name":"get all companies","description":"","method":"GET","body":{},"parameters":[],"headers":[{"name":"User-Agent","value":"insomnia/8.3.0"}],"authentication":{},"metaSortKey":-1698436574691,"isPrivate":false,"settingStoreCookies":true,"settingSendCookies":true,"settingDisableRenderRequestBody":false,"settingEncodeUrl":true,"settingRebuildPath":true,"settingFollowRedirects":"global","_type":"request"},{"_id":"req_558530025339425ea7dbfb990bd8f563","parentId":"fld_a5720f4de7914d308bc957af729c0471","modified":1698694637932,"created":1698258242001,"url":"http://localhost:3000/companies/update","name":"update company","description":"","method":"PUT","body":{"mimeType":"application/json","text":"{\n\t\t\"cpfCnpj\": \"037.440.450-05\",\n\t\t\"name\": \"teste roupas\",\n\t\t\"email\": \"teste@teste.br\",\n\t\t\"password\": \"Teste123#\",\n\t\t\"address\": \"rua sao carlos 400\",\n\t\t\"fieldOfActivity\": \"roupas\",\n\t\t\"isApproved\": false\n\t}"},"parameters":[],"headers":[{"name":"Content-Type","value":"application/json"},{"name":"User-Agent","value":"insomnia/8.3.0"}],"authentication":{},"metaSortKey":-1698436574666,"isPrivate":false,"settingStoreCookies":true,"settingSendCookies":true,"settingDisableRenderRequestBody":false,"settingEncodeUrl":true,"settingRebuildPath":true,"settingFollowRedirects":"global","_type":"request"},{"_id":"req_71d6e88596954979bd64a9e610f559a6","parentId":"fld_a5720f4de7914d308bc957af729c0471","modified":1699150211849,"created":1698258236258,"url":"http://localhost:3000/companies/delete/1","name":"delete company","description":"","method":"DELETE","body":{},"parameters":[],"headers":[{"name":"User-Agent","value":"insomnia/8.3.0"}],"authentication":{},"metaSortKey":-1698436574653.5,"isPrivate":false,"settingStoreCookies":true,"settingSendCookies":true,"settingDisableRenderRequestBody":false,"settingEncodeUrl":true,"settingRebuildPath":true,"settingFollowRedirects":"global","_type":"request"},{"_id":"req_58977c78b421446a9e5d154950ca692a","parentId":"fld_791de45225d24e36be468bb956037424","modified":1699148343033,"created":1698765839645,"url":"http://localhost:3000/superAdmin/approveCompany/1","name":"approve company","description":"","method":"GET","body":{},"parameters":[],"headers":[{"name":"User-Agent","value":"insomnia/8.3.0"}],"authentication":{},"metaSortKey":-1698765839645,"isPrivate":false,"settingStoreCookies":true,"settingSendCookies":true,"settingDisableRenderRequestBody":false,"settingEncodeUrl":true,"settingRebuildPath":true,"settingFollowRedirects":"global","_type":"request"},{"_id":"fld_791de45225d24e36be468bb956037424","parentId":"fld_8bd9c0fd9466405d9e2b935663ea5eb3","modified":1699150322454,"created":1698694525779,"name":"Super Admin","description":"","environment":{},"environmentPropertyOrder":null,"metaSortKey":-1698436686936,"_type":"request_group"},{"_id":"fld_8bd9c0fd9466405d9e2b935663ea5eb3","parentId":"wrk_cb12f0ce5b484afe8355a8cd77e1a637","modified":1698436517390,"created":1698436517390,"name":"Client","description":"","environment":{},"environmentPropertyOrder":null,"metaSortKey":-1698436517390,"_type":"request_group"},{"_id":"req_e99a59930bb84dd1aececf3ccbbd1649","parentId":"fld_791de45225d24e36be468bb956037424","modified":1698766960424,"created":1698694530921,"url":"http://localhost:3000/companies/approveNot","name":"approve not companies","description":"","method":"GET","body":{},"parameters":[],"headers":[{"name":"User-Agent","value":"insomnia/8.3.0"}],"authentication":{},"metaSortKey":-1698694530922,"isPrivate":false,"settingStoreCookies":true,"settingSendCookies":true,"settingDisableRenderRequestBody":false,"settingEncodeUrl":true,"settingRebuildPath":true,"settingFollowRedirects":"global","_type":"request"},{"_id":"req_487bfbfd9cd74578af860c2cc33ab09f","parentId":"fld_791de45225d24e36be468bb956037424","modified":1698765771992,"created":1698694922759,"url":"http://localhost:3000/companies/approved","name":"approved companies","description":"","method":"GET","body":{},"parameters":[],"headers":[{"name":"User-Agent","value":"insomnia/8.3.0"}],"authentication":{},"metaSortKey":-1698565626328.5,"isPrivate":false,"settingStoreCookies":true,"settingSendCookies":true,"settingDisableRenderRequestBody":false,"settingEncodeUrl":true,"settingRebuildPath":true,"settingFollowRedirects":"global","_type":"request"},{"_id":"req_f926028db08e41288ee91d3e5d1ceba3","parentId":"fld_fa843dd45ff145149df9ae8b4df021b2","modified":1698436742887,"created":1698256024442,"url":"http://localhost:3000/clients/create","name":"post client1","description":"","method":"POST","body":{"mimeType":"application/json","text":"{\n\t\"cpf\": \"027.440.450-05\",\n\t\"name\": \"Pedro\",\n\t\"email\": \"Pedro@Pedro.com.br\",\n\t\"password\": \"Pedro1234##\",\n\t\"address\": \"Rua São Carlos 20\",\n\t\"phoneNumber\": \"11912345678\"\n}"},"parameters":[],"headers":[{"name":"Content-Type","value":"application/json"},{"name":"User-Agent","value":"insomnia/8.3.0"}],"authentication":{},"metaSortKey":-1698436721735,"isPrivate":false,"settingStoreCookies":true,"settingSendCookies":true,"settingDisableRenderRequestBody":false,"settingEncodeUrl":true,"settingRebuildPath":true,"settingFollowRedirects":"global","_type":"request"},{"_id":"fld_fa843dd45ff145149df9ae8b4df021b2","parentId":"fld_8bd9c0fd9466405d9e2b935663ea5eb3","modified":1698436686836,"created":1698436686836,"name":"post","description":"","environment":{},"environmentPropertyOrder":null,"metaSortKey":-1698436686836,"_type":"request_group"},{"_id":"req_2d221693824c4a87b7aead40809d7ed1","parentId":"fld_fa843dd45ff145149df9ae8b4df021b2","modified":1698436945696,"created":1698436736564,"url":"http://localhost:3000/clients/create","name":"post client2","description":"","method":"POST","body":{"mimeType":"application/json","text":"{\n\t\"cpf\": \"017.440.450-05\",\n\t\"name\": \"João\",\n\t\"email\": \"Joao@Joao.com.br\",\n\t\"password\": \"Joao1234##\",\n\t\"address\": \"Rua São Carlos 20\",\n\t\"phoneNumber\": \"11912345678\"\n}"},"parameters":[],"headers":[{"name":"Content-Type","value":"application/json"},{"name":"User-Agent","value":"insomnia/8.3.0"}],"authentication":{},"metaSortKey":-1698436652400.5,"isPrivate":false,"settingStoreCookies":true,"settingSendCookies":true,"settingDisableRenderRequestBody":false,"settingEncodeUrl":true,"settingRebuildPath":true,"settingFollowRedirects":"global","_type":"request"},{"_id":"req_d00cf204077c40b9b90ae6dc67e1a84f","parentId":"fld_fa843dd45ff145149df9ae8b4df021b2","modified":1698436776398,"created":1698436759979,"url":"http://localhost:3000/clients/create","name":"post client3","description":"","method":"POST","body":{"mimeType":"application/json","text":"{\n\t\"cpf\": \"037.440.450-05\",\n\t\"name\": \"Rafael\",\n\t\"email\": \"Rafael@Rafael.com.br\",\n\t\"password\": \"Rafael1234##\",\n\t\"address\": \"Rua São Carlos 20\",\n\t\"phoneNumber\": \"11912345678\"\n}"},"parameters":[],"headers":[{"name":"Content-Type","value":"application/json"},{"name":"User-Agent","value":"insomnia/8.3.0"}],"authentication":{},"metaSortKey":-1698436617733.25,"isPrivate":false,"settingStoreCookies":true,"settingSendCookies":true,"settingDisableRenderRequestBody":false,"settingEncodeUrl":true,"settingRebuildPath":true,"settingFollowRedirects":"global","_type":"request"},{"_id":"req_754f5e9318c545bab0e7e87ff369861a","parentId":"fld_8bd9c0fd9466405d9e2b935663ea5eb3","modified":1698694659979,"created":1698258170155,"url":"http://localhost:3000/clients/search/","name":"get client by id","description":"","method":"GET","body":{},"parameters":[],"headers":[{"name":"User-Agent","value":"insomnia/8.3.0"}],"authentication":{},"metaSortKey":-1698436523008,"isPrivate":false,"settingStoreCookies":true,"settingSendCookies":true,"settingDisableRenderRequestBody":false,"settingEncodeUrl":true,"settingRebuildPath":true,"settingFollowRedirects":"global","_type":"request"},{"_id":"req_73469bdfc4844c79b9a0f20629257e18","parentId":"fld_8bd9c0fd9466405d9e2b935663ea5eb3","modified":1698436530155,"created":1698294133204,"url":"http://localhost:3000/clients/searchAll","name":"get all client","description":"","method":"GET","body":{},"parameters":[],"headers":[{"name":"User-Agent","value":"insomnia/8.3.0"}],"authentication":{},"metaSortKey":-1698436522983,"isPrivate":false,"settingStoreCookies":true,"settingSendCookies":true,"settingDisableRenderRequestBody":false,"settingEncodeUrl":true,"settingRebuildPath":true,"settingFollowRedirects":"global","_type":"request"},{"_id":"req_835d546b8d32405d8bc986224eb39226","parentId":"fld_8bd9c0fd9466405d9e2b935663ea5eb3","modified":1699157037004,"created":1699157007026,"url":"http://localhost:3000/clients/offersJoined/2","name":"get joined offers","description":"","method":"GET","body":{},"parameters":[],"headers":[{"name":"User-Agent","value":"insomnia/8.3.0"}],"authentication":{},"metaSortKey":-1698436522933,"isPrivate":false,"settingStoreCookies":true,"settingSendCookies":true,"settingDisableRenderRequestBody":false,"settingEncodeUrl":true,"settingRebuildPath":true,"settingFollowRedirects":"global","_type":"request"},{"_id":"req_e410d20393634a29bcaa6c1e6e184144","parentId":"fld_8bd9c0fd9466405d9e2b935663ea5eb3","modified":1698694665990,"created":1698299479327,"url":"http://localhost:3000/clients/update","name":"update client","description":"","method":"PUT","body":{"mimeType":"application/json","text":"{\n\t\"cpf\": \"027.440.450-05\",\n\t\"name\": \"Pedro Pedro\",\n\t\"email\": \"Pedro@Pedro.com.br\",\n\t\"password\": \"Pedro1234##\",\n\t\"address\": \"Rua São Carlos 20\",\n\t\"phoneNumber\": \"11912345678\"\n}"},"parameters":[],"headers":[{"name":"Content-Type","value":"application/json"},{"name":"User-Agent","value":"insomnia/8.3.0"}],"authentication":{},"metaSortKey":-1698436522883,"isPrivate":false,"settingStoreCookies":true,"settingSendCookies":true,"settingDisableRenderRequestBody":false,"settingEncodeUrl":true,"settingRebuildPath":true,"settingFollowRedirects":"global","_type":"request"},{"_id":"req_dea957900a464f968d555d28226f79ae","parentId":"fld_8bd9c0fd9466405d9e2b935663ea5eb3","modified":1699157670465,"created":1698258196340,"url":"http://localhost:3000/clients/delete/2","name":"delete client","description":"","method":"DELETE","body":{},"parameters":[],"headers":[{"name":"User-Agent","value":"insomnia/8.3.0"}],"authentication":{},"metaSortKey":-1698436522783,"isPrivate":false,"settingStoreCookies":true,"settingSendCookies":true,"settingDisableRenderRequestBody":false,"settingEncodeUrl":true,"settingRebuildPath":true,"settingFollowRedirects":"global","_type":"request"},{"_id":"env_1f8bfb0a36ce4586a325f76ca82b9cc6","parentId":"wrk_cb12f0ce5b484afe8355a8cd77e1a637","modified":1698256009229,"created":1698256009229,"name":"Base Environment","data":{},"dataPropertyOrder":null,"color":null,"isPrivate":false,"metaSortKey":1698256009229,"_type":"environment"},{"_id":"jar_c5c199678572467e9fe53f0e01adfb56","parentId":"wrk_cb12f0ce5b484afe8355a8cd77e1a637","modified":1698256009231,"created":1698256009231,"name":"Default Jar","cookies":[],"_type":"cookie_jar"}]}